{"frames": {

"left_attack_down-0.png":
{
	"frame": {"x":1,"y":1,"w":32,"h":32},
	"rotated": false,
	"trimmed": false,
	"spriteSourceSize": {"x":0,"y":0,"w":32,"h":32},
	"sourceSize": {"w":32,"h":32}
},
"left_attack_down-1.png":
{
	"frame": {"x":35,"y":1,"w":32,"h":32},
	"rotated": false,
	"trimmed": false,
	"spriteSourceSize": {"x":0,"y":0,"w":32,"h":32},
	"sourceSize": {"w":32,"h":32}
},
"left_attack_down-2.png":
{
	"frame": {"x":69,"y":1,"w":32,"h":32},
	"rotated": false,
	"trimmed": false,
	"spriteSourceSize": {"x":0,"y":0,"w":32,"h":32},
	"sourceSize": {"w":32,"h":32}
},
"left_attack_down-3.png":
{
	"frame": {"x":103,"y":1,"w":32,"h":32},
	"rotated": false,
	"trimmed": false,
	"spriteSourceSize": {"x":0,"y":0,"w":32,"h":32},
	"sourceSize": {"w":32,"h":32}
},
"left_attack_down-4.png":
{
	"frame": {"x":137,"y":1,"w":32,"h":32},
	"rotated": false,
	"trimmed": false,
	"spriteSourceSize": {"x":0,"y":0,"w":32,"h":32},
	"sourceSize": {"w":32,"h":32}
},
"left_attack_down-5.png":
{
	"frame": {"x":171,"y":1,"w":32,"h":32},
	"rotated": false,
	"trimmed": false,
	"spriteSourceSize": {"x":0,"y":0,"w":32,"h":32},
	"sourceSize": {"w":32,"h":32}
},
"left_attack_down-6.png":
{
	"frame": {"x":205,"y":1,"w":32,"h":32},
	"rotated": false,
	"trimmed": false,
	"spriteSourceSize": {"x":0,"y":0,"w":32,"h":32},
	"sourceSize": {"w":32,"h":32}
},
"left_attack_down-7.png":
{
	"frame": {"x":1,"y":35,"w":32,"h":32},
	"rotated": false,
	"trimmed": false,
	"spriteSourceSize": {"x":0,"y":0,"w":32,"h":32},
	"sourceSize": {"w":32,"h":32}
},
"left_attack_down-8.png":
{
	"frame": {"x":35,"y":35,"w":32,"h":32},
	"rotated": false,
	"trimmed": false,
	"spriteSourceSize": {"x":0,"y":0,"w":32,"h":32},
	"sourceSize": {"w":32,"h":32}
},
"left_attack_down-9.png":
{
	"frame": {"x":69,"y":35,"w":32,"h":32},
	"rotated": false,
	"trimmed": false,
	"spriteSourceSize": {"x":0,"y":0,"w":32,"h":32},
	"sourceSize": {"w":32,"h":32}
},
"left_attack_up-0.png":
{
	"frame": {"x":103,"y":35,"w":32,"h":32},
	"rotated": false,
	"trimmed": false,
	"spriteSourceSize": {"x":0,"y":0,"w":32,"h":32},
	"sourceSize": {"w":32,"h":32}
},
"left_attack_up-1.png":
{
	"frame": {"x":137,"y":35,"w":32,"h":32},
	"rotated": false,
	"trimmed": false,
	"spriteSourceSize": {"x":0,"y":0,"w":32,"h":32},
	"sourceSize": {"w":32,"h":32}
},
"left_attack_up-2.png":
{
	"frame": {"x":171,"y":35,"w":32,"h":32},
	"rotated": false,
	"trimmed": false,
	"spriteSourceSize": {"x":0,"y":0,"w":32,"h":32},
	"sourceSize": {"w":32,"h":32}
},
"left_attack_up-3.png":
{
	"frame": {"x":205,"y":35,"w":32,"h":32},
	"rotated": false,
	"trimmed": false,
	"spriteSourceSize": {"x":0,"y":0,"w":32,"h":32},
	"sourceSize": {"w":32,"h":32}
},
"left_attack_up-4.png":
{
	"frame": {"x":1,"y":69,"w":32,"h":32},
	"rotated": false,
	"trimmed": false,
	"spriteSourceSize": {"x":0,"y":0,"w":32,"h":32},
	"sourceSize": {"w":32,"h":32}
},
"left_attack_up-5.png":
{
	"frame": {"x":35,"y":69,"w":32,"h":32},
	"rotated": false,
	"trimmed": false,
	"spriteSourceSize": {"x":0,"y":0,"w":32,"h":32},
	"sourceSize": {"w":32,"h":32}
},
"left_attack_up-6.png":
{
	"frame": {"x":69,"y":69,"w":32,"h":32},
	"rotated": false,
	"trimmed": false,
	"spriteSourceSize": {"x":0,"y":0,"w":32,"h":32},
	"sourceSize": {"w":32,"h":32}
},
"left_attack_up-7.png":
{
	"frame": {"x":103,"y":69,"w":32,"h":32},
	"rotated": false,
	"trimmed": false,
	"spriteSourceSize": {"x":0,"y":0,"w":32,"h":32},
	"sourceSize": {"w":32,"h":32}
},
"left_attack_up-8.png":
{
	"frame": {"x":137,"y":69,"w":32,"h":32},
	"rotated": false,
	"trimmed": false,
	"spriteSourceSize": {"x":0,"y":0,"w":32,"h":32},
	"sourceSize": {"w":32,"h":32}
},
"left_attack_up-9.png":
{
	"frame": {"x":171,"y":69,"w":32,"h":32},
	"rotated": false,
	"trimmed": false,
	"spriteSourceSize": {"x":0,"y":0,"w":32,"h":32},
	"sourceSize": {"w":32,"h":32}
},
"left_being_attack-0.png":
{
	"frame": {"x":171,"y":69,"w":32,"h":32},
	"rotated": false,
	"trimmed": false,
	"spriteSourceSize": {"x":0,"y":0,"w":32,"h":32},
	"sourceSize": {"w":32,"h":32}
},
"left_being_attack-1.png":
{
	"frame": {"x":205,"y":69,"w":32,"h":32},
	"rotated": false,
	"trimmed": false,
	"spriteSourceSize": {"x":0,"y":0,"w":32,"h":32},
	"sourceSize": {"w":32,"h":32}
},
"left_being_attack-2.png":
{
	"frame": {"x":1,"y":103,"w":32,"h":32},
	"rotated": false,
	"trimmed": false,
	"spriteSourceSize": {"x":0,"y":0,"w":32,"h":32},
	"sourceSize": {"w":32,"h":32}
},
"left_being_attack-3.png":
{
	"frame": {"x":35,"y":103,"w":32,"h":32},
	"rotated": false,
	"trimmed": false,
	"spriteSourceSize": {"x":0,"y":0,"w":32,"h":32},
	"sourceSize": {"w":32,"h":32}
},
"left_idle-0.png":
{
	"frame": {"x":171,"y":69,"w":32,"h":32},
	"rotated": false,
	"trimmed": false,
	"spriteSourceSize": {"x":0,"y":0,"w":32,"h":32},
	"sourceSize": {"w":32,"h":32}
},
"left_idle-1.png":
{
	"frame": {"x":69,"y":103,"w":32,"h":32},
	"rotated": false,
	"trimmed": false,
	"spriteSourceSize": {"x":0,"y":0,"w":32,"h":32},
	"sourceSize": {"w":32,"h":32}
},
"left_idle-2.png":
{
	"frame": {"x":137,"y":103,"w":32,"h":32},
	"rotated": false,
	"trimmed": false,
	"spriteSourceSize": {"x":0,"y":0,"w":32,"h":32},
	"sourceSize": {"w":32,"h":32}
},
"left_idle-3.png":
{
	"frame": {"x":171,"y":103,"w":32,"h":32},
	"rotated": false,
	"trimmed": false,
	"spriteSourceSize": {"x":0,"y":0,"w":32,"h":32},
	"sourceSize": {"w":32,"h":32}
},
"left_idle-4.png":
{
	"frame": {"x":205,"y":103,"w":32,"h":32},
	"rotated": false,
	"trimmed": false,
	"spriteSourceSize": {"x":0,"y":0,"w":32,"h":32},
	"sourceSize": {"w":32,"h":32}
},
"left_idle-5.png":
{
	"frame": {"x":1,"y":137,"w":32,"h":32},
	"rotated": false,
	"trimmed": false,
	"spriteSourceSize": {"x":0,"y":0,"w":32,"h":32},
	"sourceSize": {"w":32,"h":32}
},
"left_idle-6.png":
{
	"frame": {"x":1,"y":137,"w":32,"h":32},
	"rotated": false,
	"trimmed": false,
	"spriteSourceSize": {"x":0,"y":0,"w":32,"h":32},
	"sourceSize": {"w":32,"h":32}
},
"left_idle-7.png":
{
	"frame": {"x":205,"y":103,"w":32,"h":32},
	"rotated": false,
	"trimmed": false,
	"spriteSourceSize": {"x":0,"y":0,"w":32,"h":32},
	"sourceSize": {"w":32,"h":32}
},
"left_idle-8.png":
{
	"frame": {"x":205,"y":103,"w":32,"h":32},
	"rotated": false,
	"trimmed": false,
	"spriteSourceSize": {"x":0,"y":0,"w":32,"h":32},
	"sourceSize": {"w":32,"h":32}
},
"left_idle-9.png":
{
	"frame": {"x":35,"y":137,"w":32,"h":32},
	"rotated": false,
	"trimmed": false,
	"spriteSourceSize": {"x":0,"y":0,"w":32,"h":32},
	"sourceSize": {"w":32,"h":32}
},
"left_idle-10.png":
{
	"frame": {"x":103,"y":103,"w":32,"h":32},
	"rotated": false,
	"trimmed": false,
	"spriteSourceSize": {"x":0,"y":0,"w":32,"h":32},
	"sourceSize": {"w":32,"h":32}
},
"left_idle-11.png":
{
	"frame": {"x":171,"y":69,"w":32,"h":32},
	"rotated": false,
	"trimmed": false,
	"spriteSourceSize": {"x":0,"y":0,"w":32,"h":32},
	"sourceSize": {"w":32,"h":32}
},
"left_idle-12.png":
{
	"frame": {"x":171,"y":69,"w":32,"h":32},
	"rotated": false,
	"trimmed": false,
	"spriteSourceSize": {"x":0,"y":0,"w":32,"h":32},
	"sourceSize": {"w":32,"h":32}
},
"left_jump-0.png":
{
	"frame": {"x":171,"y":69,"w":32,"h":32},
	"rotated": false,
	"trimmed": false,
	"spriteSourceSize": {"x":0,"y":0,"w":32,"h":32},
	"sourceSize": {"w":32,"h":32}
},
"left_jump-1.png":
{
	"frame": {"x":69,"y":137,"w":32,"h":32},
	"rotated": false,
	"trimmed": false,
	"spriteSourceSize": {"x":0,"y":0,"w":32,"h":32},
	"sourceSize": {"w":32,"h":32}
},
"left_jump-2.png":
{
	"frame": {"x":103,"y":137,"w":32,"h":32},
	"rotated": false,
	"trimmed": false,
	"spriteSourceSize": {"x":0,"y":0,"w":32,"h":32},
	"sourceSize": {"w":32,"h":32}
},
"left_jump-3.png":
{
	"frame": {"x":137,"y":137,"w":32,"h":32},
	"rotated": false,
	"trimmed": false,
	"spriteSourceSize": {"x":0,"y":0,"w":32,"h":32},
	"sourceSize": {"w":32,"h":32}
},
"left_jump-4.png":
{
	"frame": {"x":171,"y":137,"w":32,"h":32},
	"rotated": false,
	"trimmed": false,
	"spriteSourceSize": {"x":0,"y":0,"w":32,"h":32},
	"sourceSize": {"w":32,"h":32}
},
"left_jump-5.png":
{
	"frame": {"x":69,"y":137,"w":32,"h":32},
	"rotated": false,
	"trimmed": false,
	"spriteSourceSize": {"x":0,"y":0,"w":32,"h":32},
	"sourceSize": {"w":32,"h":32}
},
"left_jump_attack-0.png":
{
	"frame": {"x":205,"y":137,"w":32,"h":32},
	"rotated": false,
	"trimmed": false,
	"spriteSourceSize": {"x":0,"y":0,"w":32,"h":32},
	"sourceSize": {"w":32,"h":32}
},
"left_jump_attack-1.png":
{
	"frame": {"x":1,"y":171,"w":32,"h":32},
	"rotated": false,
	"trimmed": false,
	"spriteSourceSize": {"x":0,"y":0,"w":32,"h":32},
	"sourceSize": {"w":32,"h":32}
},
"left_jump_attack-2.png":
{
	"frame": {"x":35,"y":171,"w":32,"h":32},
	"rotated": false,
	"trimmed": false,
	"spriteSourceSize": {"x":0,"y":0,"w":32,"h":32},
	"sourceSize": {"w":32,"h":32}
},
"left_jump_attack-3.png":
{
	"frame": {"x":69,"y":171,"w":32,"h":32},
	"rotated": false,
	"trimmed": false,
	"spriteSourceSize": {"x":0,"y":0,"w":32,"h":32},
	"sourceSize": {"w":32,"h":32}
},
"left_jump_attack-4.png":
{
	"frame": {"x":103,"y":171,"w":32,"h":32},
	"rotated": false,
	"trimmed": false,
	"spriteSourceSize": {"x":0,"y":0,"w":32,"h":32},
	"sourceSize": {"w":32,"h":32}
},
"left_jump_attack-5.png":
{
	"frame": {"x":137,"y":171,"w":32,"h":32},
	"rotated": false,
	"trimmed": false,
	"spriteSourceSize": {"x":0,"y":0,"w":32,"h":32},
	"sourceSize": {"w":32,"h":32}
},
"left_jump_attack-6.png":
{
	"frame": {"x":69,"y":69,"w":32,"h":32},
	"rotated": false,
	"trimmed": false,
	"spriteSourceSize": {"x":0,"y":0,"w":32,"h":32},
	"sourceSize": {"w":32,"h":32}
},
"left_jump_attack-7.png":
{
	"frame": {"x":103,"y":69,"w":32,"h":32},
	"rotated": false,
	"trimmed": false,
	"spriteSourceSize": {"x":0,"y":0,"w":32,"h":32},
	"sourceSize": {"w":32,"h":32}
},
"left_jump_attack-8.png":
{
	"frame": {"x":137,"y":69,"w":32,"h":32},
	"rotated": false,
	"trimmed": false,
	"spriteSourceSize": {"x":0,"y":0,"w":32,"h":32},
	"sourceSize": {"w":32,"h":32}
},
"left_jump_attack-9.png":
{
	"frame": {"x":171,"y":69,"w":32,"h":32},
	"rotated": false,
	"trimmed": false,
	"spriteSourceSize": {"x":0,"y":0,"w":32,"h":32},
	"sourceSize": {"w":32,"h":32}
},
"left_lay_down-0.png":
{
	"frame": {"x":171,"y":69,"w":32,"h":32},
	"rotated": false,
	"trimmed": false,
	"spriteSourceSize": {"x":0,"y":0,"w":32,"h":32},
	"sourceSize": {"w":32,"h":32}
},
"left_lay_down-1.png":
{
	"frame": {"x":205,"y":69,"w":32,"h":32},
	"rotated": false,
	"trimmed": false,
	"spriteSourceSize": {"x":0,"y":0,"w":32,"h":32},
	"sourceSize": {"w":32,"h":32}
},
"left_lay_down-2.png":
{
	"frame": {"x":1,"y":103,"w":32,"h":32},
	"rotated": false,
	"trimmed": false,
	"spriteSourceSize": {"x":0,"y":0,"w":32,"h":32},
	"sourceSize": {"w":32,"h":32}
},
"left_lay_down-3.png":
{
	"frame": {"x":171,"y":171,"w":32,"h":32},
	"rotated": false,
	"trimmed": false,
	"spriteSourceSize": {"x":0,"y":0,"w":32,"h":32},
	"sourceSize": {"w":32,"h":32}
},
"left_lay_down-4.png":
{
	"frame": {"x":205,"y":171,"w":32,"h":32},
	"rotated": false,
	"trimmed": false,
	"spriteSourceSize": {"x":0,"y":0,"w":32,"h":32},
	"sourceSize": {"w":32,"h":32}
},
"left_lay_down-5.png":
{
	"frame": {"x":1,"y":205,"w":32,"h":32},
	"rotated": false,
	"trimmed": false,
	"spriteSourceSize": {"x":0,"y":0,"w":32,"h":32},
	"sourceSize": {"w":32,"h":32}
},
"left_lay_down-6.png":
{
	"frame": {"x":35,"y":205,"w":32,"h":32},
	"rotated": false,
	"trimmed": false,
	"spriteSourceSize": {"x":0,"y":0,"w":32,"h":32},
	"sourceSize": {"w":32,"h":32}
},
"left_run-0.png":
{
	"frame": {"x":69,"y":205,"w":32,"h":32},
	"rotated": false,
	"trimmed": false,
	"spriteSourceSize": {"x":0,"y":0,"w":32,"h":32},
	"sourceSize": {"w":32,"h":32}
},
"left_run-1.png":
{
	"frame": {"x":103,"y":205,"w":32,"h":32},
	"rotated": false,
	"trimmed": false,
	"spriteSourceSize": {"x":0,"y":0,"w":32,"h":32},
	"sourceSize": {"w":32,"h":32}
},
"left_run-2.png":
{
	"frame": {"x":137,"y":205,"w":32,"h":32},
	"rotated": false,
	"trimmed": false,
	"spriteSourceSize": {"x":0,"y":0,"w":32,"h":32},
	"sourceSize": {"w":32,"h":32}
},
"left_run-3.png":
{
	"frame": {"x":171,"y":205,"w":32,"h":32},
	"rotated": false,
	"trimmed": false,
	"spriteSourceSize": {"x":0,"y":0,"w":32,"h":32},
	"sourceSize": {"w":32,"h":32}
},
"left_run-4.png":
{
	"frame": {"x":205,"y":205,"w":32,"h":32},
	"rotated": false,
	"trimmed": false,
	"spriteSourceSize": {"x":0,"y":0,"w":32,"h":32},
	"sourceSize": {"w":32,"h":32}
},
"left_run-5.png":
{
	"frame": {"x":1,"y":239,"w":32,"h":32},
	"rotated": false,
	"trimmed": false,
	"spriteSourceSize": {"x":0,"y":0,"w":32,"h":32},
	"sourceSize": {"w":32,"h":32}
},
"left_run-6.png":
{
	"frame": {"x":205,"y":205,"w":32,"h":32},
	"rotated": false,
	"trimmed": false,
	"spriteSourceSize": {"x":0,"y":0,"w":32,"h":32},
	"sourceSize": {"w":32,"h":32}
},
"left_run-7.png":
{
	"frame": {"x":171,"y":205,"w":32,"h":32},
	"rotated": false,
	"trimmed": false,
	"spriteSourceSize": {"x":0,"y":0,"w":32,"h":32},
	"sourceSize": {"w":32,"h":32}
},
"right_attack_down-0.png":
{
	"frame": {"x":35,"y":239,"w":32,"h":32},
	"rotated": false,
	"trimmed": false,
	"spriteSourceSize": {"x":0,"y":0,"w":32,"h":32},
	"sourceSize": {"w":32,"h":32}
},
"right_attack_down-1.png":
{
	"frame": {"x":69,"y":239,"w":32,"h":32},
	"rotated": false,
	"trimmed": false,
	"spriteSourceSize": {"x":0,"y":0,"w":32,"h":32},
	"sourceSize": {"w":32,"h":32}
},
"right_attack_down-2.png":
{
	"frame": {"x":103,"y":239,"w":32,"h":32},
	"rotated": false,
	"trimmed": false,
	"spriteSourceSize": {"x":0,"y":0,"w":32,"h":32},
	"sourceSize": {"w":32,"h":32}
},
"right_attack_down-3.png":
{
	"frame": {"x":137,"y":239,"w":32,"h":32},
	"rotated": false,
	"trimmed": false,
	"spriteSourceSize": {"x":0,"y":0,"w":32,"h":32},
	"sourceSize": {"w":32,"h":32}
},
"right_attack_down-4.png":
{
	"frame": {"x":171,"y":239,"w":32,"h":32},
	"rotated": false,
	"trimmed": false,
	"spriteSourceSize": {"x":0,"y":0,"w":32,"h":32},
	"sourceSize": {"w":32,"h":32}
},
"right_attack_down-5.png":
{
	"frame": {"x":205,"y":239,"w":32,"h":32},
	"rotated": false,
	"trimmed": false,
	"spriteSourceSize": {"x":0,"y":0,"w":32,"h":32},
	"sourceSize": {"w":32,"h":32}
},
"right_attack_down-6.png":
{
	"frame": {"x":1,"y":273,"w":32,"h":32},
	"rotated": false,
	"trimmed": false,
	"spriteSourceSize": {"x":0,"y":0,"w":32,"h":32},
	"sourceSize": {"w":32,"h":32}
},
"right_attack_down-7.png":
{
	"frame": {"x":1,"y":307,"w":32,"h":32},
	"rotated": false,
	"trimmed": false,
	"spriteSourceSize": {"x":0,"y":0,"w":32,"h":32},
	"sourceSize": {"w":32,"h":32}
},
"right_attack_down-8.png":
{
	"frame": {"x":1,"y":341,"w":32,"h":32},
	"rotated": false,
	"trimmed": false,
	"spriteSourceSize": {"x":0,"y":0,"w":32,"h":32},
	"sourceSize": {"w":32,"h":32}
},
"right_attack_down-9.png":
{
	"frame": {"x":1,"y":375,"w":32,"h":32},
	"rotated": false,
	"trimmed": false,
	"spriteSourceSize": {"x":0,"y":0,"w":32,"h":32},
	"sourceSize": {"w":32,"h":32}
},
"right_attack_up-0.png":
{
	"frame": {"x":1,"y":409,"w":32,"h":32},
	"rotated": false,
	"trimmed": false,
	"spriteSourceSize": {"x":0,"y":0,"w":32,"h":32},
	"sourceSize": {"w":32,"h":32}
},
"right_attack_up-1.png":
{
	"frame": {"x":1,"y":443,"w":32,"h":32},
	"rotated": false,
	"trimmed": false,
	"spriteSourceSize": {"x":0,"y":0,"w":32,"h":32},
	"sourceSize": {"w":32,"h":32}
},
"right_attack_up-2.png":
{
	"frame": {"x":1,"y":477,"w":32,"h":32},
	"rotated": false,
	"trimmed": false,
	"spriteSourceSize": {"x":0,"y":0,"w":32,"h":32},
	"sourceSize": {"w":32,"h":32}
},
"right_attack_up-3.png":
{
	"frame": {"x":35,"y":273,"w":32,"h":32},
	"rotated": false,
	"trimmed": false,
	"spriteSourceSize": {"x":0,"y":0,"w":32,"h":32},
	"sourceSize": {"w":32,"h":32}
},
"right_attack_up-4.png":
{
	"frame": {"x":69,"y":273,"w":32,"h":32},
	"rotated": false,
	"trimmed": false,
	"spriteSourceSize": {"x":0,"y":0,"w":32,"h":32},
	"sourceSize": {"w":32,"h":32}
},
"right_attack_up-5.png":
{
	"frame": {"x":103,"y":273,"w":32,"h":32},
	"rotated": false,
	"trimmed": false,
	"spriteSourceSize": {"x":0,"y":0,"w":32,"h":32},
	"sourceSize": {"w":32,"h":32}
},
"right_attack_up-6.png":
{
	"frame": {"x":137,"y":273,"w":32,"h":32},
	"rotated": false,
	"trimmed": false,
	"spriteSourceSize": {"x":0,"y":0,"w":32,"h":32},
	"sourceSize": {"w":32,"h":32}
},
"right_attack_up-7.png":
{
	"frame": {"x":171,"y":273,"w":32,"h":32},
	"rotated": false,
	"trimmed": false,
	"spriteSourceSize": {"x":0,"y":0,"w":32,"h":32},
	"sourceSize": {"w":32,"h":32}
},
"right_attack_up-8.png":
{
	"frame": {"x":205,"y":273,"w":32,"h":32},
	"rotated": false,
	"trimmed": false,
	"spriteSourceSize": {"x":0,"y":0,"w":32,"h":32},
	"sourceSize": {"w":32,"h":32}
},
"right_attack_up-9.png":
{
	"frame": {"x":35,"y":307,"w":32,"h":32},
	"rotated": false,
	"trimmed": false,
	"spriteSourceSize": {"x":0,"y":0,"w":32,"h":32},
	"sourceSize": {"w":32,"h":32}
},
"right_being_attack-0.png":
{
	"frame": {"x":35,"y":307,"w":32,"h":32},
	"rotated": false,
	"trimmed": false,
	"spriteSourceSize": {"x":0,"y":0,"w":32,"h":32},
	"sourceSize": {"w":32,"h":32}
},
"right_being_attack-1.png":
{
	"frame": {"x":35,"y":341,"w":32,"h":32},
	"rotated": false,
	"trimmed": false,
	"spriteSourceSize": {"x":0,"y":0,"w":32,"h":32},
	"sourceSize": {"w":32,"h":32}
},
"right_being_attack-2.png":
{
	"frame": {"x":35,"y":375,"w":32,"h":32},
	"rotated": false,
	"trimmed": false,
	"spriteSourceSize": {"x":0,"y":0,"w":32,"h":32},
	"sourceSize": {"w":32,"h":32}
},
"right_being_attack-3.png":
{
	"frame": {"x":35,"y":409,"w":32,"h":32},
	"rotated": false,
	"trimmed": false,
	"spriteSourceSize": {"x":0,"y":0,"w":32,"h":32},
	"sourceSize": {"w":32,"h":32}
},
"right_idle-0.png":
{
	"frame": {"x":35,"y":307,"w":32,"h":32},
	"rotated": false,
	"trimmed": false,
	"spriteSourceSize": {"x":0,"y":0,"w":32,"h":32},
	"sourceSize": {"w":32,"h":32}
},
"right_idle-1.png":
{
	"frame": {"x":35,"y":443,"w":32,"h":32},
	"rotated": false,
	"trimmed": false,
	"spriteSourceSize": {"x":0,"y":0,"w":32,"h":32},
	"sourceSize": {"w":32,"h":32}
},
"right_idle-2.png":
{
	"frame": {"x":69,"y":307,"w":32,"h":32},
	"rotated": false,
	"trimmed": false,
	"spriteSourceSize": {"x":0,"y":0,"w":32,"h":32},
	"sourceSize": {"w":32,"h":32}
},
"right_idle-3.png":
{
	"frame": {"x":103,"y":307,"w":32,"h":32},
	"rotated": false,
	"trimmed": false,
	"spriteSourceSize": {"x":0,"y":0,"w":32,"h":32},
	"sourceSize": {"w":32,"h":32}
},
"right_idle-4.png":
{
	"frame": {"x":137,"y":307,"w":32,"h":32},
	"rotated": false,
	"trimmed": false,
	"spriteSourceSize": {"x":0,"y":0,"w":32,"h":32},
	"sourceSize": {"w":32,"h":32}
},
"right_idle-5.png":
{
	"frame": {"x":171,"y":307,"w":32,"h":32},
	"rotated": false,
	"trimmed": false,
	"spriteSourceSize": {"x":0,"y":0,"w":32,"h":32},
	"sourceSize": {"w":32,"h":32}
},
"right_idle-6.png":
{
	"frame": {"x":171,"y":307,"w":32,"h":32},
	"rotated": false,
	"trimmed": false,
	"spriteSourceSize": {"x":0,"y":0,"w":32,"h":32},
	"sourceSize": {"w":32,"h":32}
},
"right_idle-7.png":
{
	"frame": {"x":137,"y":307,"w":32,"h":32},
	"rotated": false,
	"trimmed": false,
	"spriteSourceSize": {"x":0,"y":0,"w":32,"h":32},
	"sourceSize": {"w":32,"h":32}
},
"right_idle-8.png":
{
	"frame": {"x":137,"y":307,"w":32,"h":32},
	"rotated": false,
	"trimmed": false,
	"spriteSourceSize": {"x":0,"y":0,"w":32,"h":32},
	"sourceSize": {"w":32,"h":32}
},
"right_idle-9.png":
{
	"frame": {"x":205,"y":307,"w":32,"h":32},
	"rotated": false,
	"trimmed": false,
	"spriteSourceSize": {"x":0,"y":0,"w":32,"h":32},
	"sourceSize": {"w":32,"h":32}
},
"right_idle-10.png":
{
	"frame": {"x":35,"y":477,"w":32,"h":32},
	"rotated": false,
	"trimmed": false,
	"spriteSourceSize": {"x":0,"y":0,"w":32,"h":32},
	"sourceSize": {"w":32,"h":32}
},
"right_idle-11.png":
{
	"frame": {"x":35,"y":307,"w":32,"h":32},
	"rotated": false,
	"trimmed": false,
	"spriteSourceSize": {"x":0,"y":0,"w":32,"h":32},
	"sourceSize": {"w":32,"h":32}
},
"right_idle-12.png":
{
	"frame": {"x":35,"y":307,"w":32,"h":32},
	"rotated": false,
	"trimmed": false,
	"spriteSourceSize": {"x":0,"y":0,"w":32,"h":32},
	"sourceSize": {"w":32,"h":32}
},
"right_jump-0.png":
{
	"frame": {"x":35,"y":307,"w":32,"h":32},
	"rotated": false,
	"trimmed": false,
	"spriteSourceSize": {"x":0,"y":0,"w":32,"h":32},
	"sourceSize": {"w":32,"h":32}
},
"right_jump-1.png":
{
	"frame": {"x":69,"y":341,"w":32,"h":32},
	"rotated": false,
	"trimmed": false,
	"spriteSourceSize": {"x":0,"y":0,"w":32,"h":32},
	"sourceSize": {"w":32,"h":32}
},
"right_jump-2.png":
{
	"frame": {"x":69,"y":375,"w":32,"h":32},
	"rotated": false,
	"trimmed": false,
	"spriteSourceSize": {"x":0,"y":0,"w":32,"h":32},
	"sourceSize": {"w":32,"h":32}
},
"right_jump-3.png":
{
	"frame": {"x":69,"y":409,"w":32,"h":32},
	"rotated": false,
	"trimmed": false,
	"spriteSourceSize": {"x":0,"y":0,"w":32,"h":32},
	"sourceSize": {"w":32,"h":32}
},
"right_jump-4.png":
{
	"frame": {"x":69,"y":443,"w":32,"h":32},
	"rotated": false,
	"trimmed": false,
	"spriteSourceSize": {"x":0,"y":0,"w":32,"h":32},
	"sourceSize": {"w":32,"h":32}
},
"right_jump-5.png":
{
	"frame": {"x":69,"y":341,"w":32,"h":32},
	"rotated": false,
	"trimmed": false,
	"spriteSourceSize": {"x":0,"y":0,"w":32,"h":32},
	"sourceSize": {"w":32,"h":32}
},
"right_jump_attack-0.png":
{
	"frame": {"x":69,"y":477,"w":32,"h":32},
	"rotated": false,
	"trimmed": false,
	"spriteSourceSize": {"x":0,"y":0,"w":32,"h":32},
	"sourceSize": {"w":32,"h":32}
},
"right_jump_attack-1.png":
{
	"frame": {"x":103,"y":341,"w":32,"h":32},
	"rotated": false,
	"trimmed": false,
	"spriteSourceSize": {"x":0,"y":0,"w":32,"h":32},
	"sourceSize": {"w":32,"h":32}
},
"right_jump_attack-2.png":
{
	"frame": {"x":137,"y":341,"w":32,"h":32},
	"rotated": false,
	"trimmed": false,
	"spriteSourceSize": {"x":0,"y":0,"w":32,"h":32},
	"sourceSize": {"w":32,"h":32}
},
"right_jump_attack-3.png":
{
	"frame": {"x":171,"y":341,"w":32,"h":32},
	"rotated": false,
	"trimmed": false,
	"spriteSourceSize": {"x":0,"y":0,"w":32,"h":32},
	"sourceSize": {"w":32,"h":32}
},
"right_jump_attack-4.png":
{
	"frame": {"x":205,"y":341,"w":32,"h":32},
	"rotated": false,
	"trimmed": false,
	"spriteSourceSize": {"x":0,"y":0,"w":32,"h":32},
	"sourceSize": {"w":32,"h":32}
},
"right_jump_attack-5.png":
{
	"frame": {"x":103,"y":375,"w":32,"h":32},
	"rotated": false,
	"trimmed": false,
	"spriteSourceSize": {"x":0,"y":0,"w":32,"h":32},
	"sourceSize": {"w":32,"h":32}
},
"right_jump_attack-6.png":
{
	"frame": {"x":137,"y":273,"w":32,"h":32},
	"rotated": false,
	"trimmed": false,
	"spriteSourceSize": {"x":0,"y":0,"w":32,"h":32},
	"sourceSize": {"w":32,"h":32}
},
"right_jump_attack-7.png":
{
	"frame": {"x":171,"y":273,"w":32,"h":32},
	"rotated": false,
	"trimmed": false,
	"spriteSourceSize": {"x":0,"y":0,"w":32,"h":32},
	"sourceSize": {"w":32,"h":32}
},
"right_jump_attack-8.png":
{
	"frame": {"x":205,"y":273,"w":32,"h":32},
	"rotated": false,
	"trimmed": false,
	"spriteSourceSize": {"x":0,"y":0,"w":32,"h":32},
	"sourceSize": {"w":32,"h":32}
},
"right_jump_attack-9.png":
{
	"frame": {"x":35,"y":307,"w":32,"h":32},
	"rotated": false,
	"trimmed": false,
	"spriteSourceSize": {"x":0,"y":0,"w":32,"h":32},
	"sourceSize": {"w":32,"h":32}
},
"right_lay_down-0.png":
{
	"frame": {"x":35,"y":307,"w":32,"h":32},
	"rotated": false,
	"trimmed": false,
	"spriteSourceSize": {"x":0,"y":0,"w":32,"h":32},
	"sourceSize": {"w":32,"h":32}
},
"right_lay_down-1.png":
{
	"frame": {"x":35,"y":341,"w":32,"h":32},
	"rotated": false,
	"trimmed": false,
	"spriteSourceSize": {"x":0,"y":0,"w":32,"h":32},
	"sourceSize": {"w":32,"h":32}
},
"right_lay_down-2.png":
{
	"frame": {"x":35,"y":375,"w":32,"h":32},
	"rotated": false,
	"trimmed": false,
	"spriteSourceSize": {"x":0,"y":0,"w":32,"h":32},
	"sourceSize": {"w":32,"h":32}
},
"right_lay_down-3.png":
{
	"frame": {"x":103,"y":409,"w":32,"h":32},
	"rotated": false,
	"trimmed": false,
	"spriteSourceSize": {"x":0,"y":0,"w":32,"h":32},
	"sourceSize": {"w":32,"h":32}
},
"right_lay_down-4.png":
{
	"frame": {"x":103,"y":443,"w":32,"h":32},
	"rotated": false,
	"trimmed": false,
	"spriteSourceSize": {"x":0,"y":0,"w":32,"h":32},
	"sourceSize": {"w":32,"h":32}
},
"right_lay_down-5.png":
{
	"frame": {"x":103,"y":477,"w":32,"h":32},
	"rotated": false,
	"trimmed": false,
	"spriteSourceSize": {"x":0,"y":0,"w":32,"h":32},
	"sourceSize": {"w":32,"h":32}
},
"right_lay_down-6.png":
{
	"frame": {"x":137,"y":375,"w":32,"h":32},
	"rotated": false,
	"trimmed": false,
	"spriteSourceSize": {"x":0,"y":0,"w":32,"h":32},
	"sourceSize": {"w":32,"h":32}
},
"right_run-0.png":
{
	"frame": {"x":171,"y":375,"w":32,"h":32},
	"rotated": false,
	"trimmed": false,
	"spriteSourceSize": {"x":0,"y":0,"w":32,"h":32},
	"sourceSize": {"w":32,"h":32}
},
"right_run-1.png":
{
	"frame": {"x":205,"y":375,"w":32,"h":32},
	"rotated": false,
	"trimmed": false,
	"spriteSourceSize": {"x":0,"y":0,"w":32,"h":32},
	"sourceSize": {"w":32,"h":32}
},
"right_run-2.png":
{
	"frame": {"x":137,"y":409,"w":32,"h":32},
	"rotated": false,
	"trimmed": false,
	"spriteSourceSize": {"x":0,"y":0,"w":32,"h":32},
	"sourceSize": {"w":32,"h":32}
},
"right_run-3.png":
{
	"frame": {"x":137,"y":443,"w":32,"h":32},
	"rotated": false,
	"trimmed": false,
	"spriteSourceSize": {"x":0,"y":0,"w":32,"h":32},
	"sourceSize": {"w":32,"h":32}
},
"right_run-4.png":
{
	"frame": {"x":137,"y":477,"w":32,"h":32},
	"rotated": false,
	"trimmed": false,
	"spriteSourceSize": {"x":0,"y":0,"w":32,"h":32},
	"sourceSize": {"w":32,"h":32}
},
"right_run-5.png":
{
	"frame": {"x":171,"y":409,"w":32,"h":32},
	"rotated": false,
	"trimmed": false,
	"spriteSourceSize": {"x":0,"y":0,"w":32,"h":32},
	"sourceSize": {"w":32,"h":32}
},
"right_run-6.png":
{
	"frame": {"x":137,"y":477,"w":32,"h":32},
	"rotated": false,
	"trimmed": false,
	"spriteSourceSize": {"x":0,"y":0,"w":32,"h":32},
	"sourceSize": {"w":32,"h":32}
},
"right_run-7.png":
{
	"frame": {"x":137,"y":443,"w":32,"h":32},
	"rotated": false,
	"trimmed": false,
	"spriteSourceSize": {"x":0,"y":0,"w":32,"h":32},
	"sourceSize": {"w":32,"h":32}
}},
"animations": {
	"left_attack_down": ["left_attack_down-0.png","left_attack_down-1.png","left_attack_down-2.png","left_attack_down-3.png","left_attack_down-4.png","left_attack_down-5.png","left_attack_down-6.png","left_attack_down-7.png","left_attack_down-8.png","left_attack_down-9.png"],
	"left_attack_up": ["left_attack_up-0.png","left_attack_up-1.png","left_attack_up-2.png","left_attack_up-3.png","left_attack_up-4.png","left_attack_up-5.png","left_attack_up-6.png","left_attack_up-7.png","left_attack_up-8.png","left_attack_up-9.png"],
	"left_being_attack": ["left_being_attack-0.png","left_being_attack-1.png","left_being_attack-2.png","left_being_attack-3.png"],
	"left_idle": ["left_idle-0.png","left_idle-1.png","left_idle-2.png","left_idle-3.png","left_idle-4.png","left_idle-5.png","left_idle-6.png","left_idle-7.png","left_idle-8.png","left_idle-9.png","left_idle-10.png","left_idle-11.png","left_idle-12.png"],
	"left_jump": ["left_jump-0.png","left_jump-1.png","left_jump-2.png","left_jump-3.png","left_jump-4.png","left_jump-5.png"],
	"left_jump_attack": ["left_jump_attack-0.png","left_jump_attack-1.png","left_jump_attack-2.png","left_jump_attack-3.png","left_jump_attack-4.png","left_jump_attack-5.png","left_jump_attack-6.png","left_jump_attack-7.png","left_jump_attack-8.png","left_jump_attack-9.png"],
	"left_lay_down": ["left_lay_down-0.png","left_lay_down-1.png","left_lay_down-2.png","left_lay_down-3.png","left_lay_down-4.png","left_lay_down-5.png","left_lay_down-6.png"],
	"left_run": ["left_run-0.png","left_run-1.png","left_run-2.png","left_run-3.png","left_run-4.png","left_run-5.png","left_run-6.png","left_run-7.png"],
	"right_attack_down": ["right_attack_down-0.png","right_attack_down-1.png","right_attack_down-2.png","right_attack_down-3.png","right_attack_down-4.png","right_attack_down-5.png","right_attack_down-6.png","right_attack_down-7.png","right_attack_down-8.png","right_attack_down-9.png"],
	"right_attack_up": ["right_attack_up-0.png","right_attack_up-1.png","right_attack_up-2.png","right_attack_up-3.png","right_attack_up-4.png","right_attack_up-5.png","right_attack_up-6.png","right_attack_up-7.png","right_attack_up-8.png","right_attack_up-9.png"],
	"right_being_attack": ["right_being_attack-0.png","right_being_attack-1.png","right_being_attack-2.png","right_being_attack-3.png"],
	"right_idle": ["right_idle-0.png","right_idle-1.png","right_idle-2.png","right_idle-3.png","right_idle-4.png","right_idle-5.png","right_idle-6.png","right_idle-7.png","right_idle-8.png","right_idle-9.png","right_idle-10.png","right_idle-11.png","right_idle-12.png"],
	"right_jump": ["right_jump-0.png","right_jump-1.png","right_jump-2.png","right_jump-3.png","right_jump-4.png","right_jump-5.png"],
	"right_jump_attack": ["right_jump_attack-0.png","right_jump_attack-1.png","right_jump_attack-2.png","right_jump_attack-3.png","right_jump_attack-4.png","right_jump_attack-5.png","right_jump_attack-6.png","right_jump_attack-7.png","right_jump_attack-8.png","right_jump_attack-9.png"],
	"right_lay_down": ["right_lay_down-0.png","right_lay_down-1.png","right_lay_down-2.png","right_lay_down-3.png","right_lay_down-4.png","right_lay_down-5.png","right_lay_down-6.png"],
	"right_run": ["right_run-0.png","right_run-1.png","right_run-2.png","right_run-3.png","right_run-4.png","right_run-5.png","right_run-6.png","right_run-7.png"]
},
"meta": {
	"app": "https://www.codeandweb.com/texturepacker",
	"version": "1.0",
	"image": "adventurer.png",
	"format": "RGBA8888",
	"size": {"w":256,"h":512},
	"scale": "1",
	"smartupdate": "$TexturePacker:SmartUpdate:a0a2bf1a3b18a0c0c66b33169ce6f499:21ece3d0ace7fe25a0d7167427408b0e:932c9555d40b6febc8dc495067cbaa4d$"
}
}
